setup.py
pyflot/__init__.py
python_flot_utils.egg-info/PKG-INFO
python_flot_utils.egg-info/SOURCES.txt
python_flot_utils.egg-info/dependency_links.txt
python_flot_utils.egg-info/top_level.txt
tests/__init__.py