Metadata-Version: 1.0
Name: python-flot-utils
Version: 0.2
Summary: Makes it easy to convert Python data structures to JSON strings suitable for flot series and options
Home-page: UNKNOWN
Author: Brian Luft
Author-email: brian@unbracketed.com
License: MIT
Keywords: flot graphs charts javascript data timeseries time series
Platform: UNKNOWN
Classifier: Development Status :: 3 - Alpha
Classifier: Topic :: Utilities
Classifier: License :: OSI Approved :: MIT License
